automated_logging/__init__.py
automated_logging/admin/__init__.py
automated_logging/admin/base.py
automated_logging/admin/model_entry.py
automated_logging/admin/model_event.py
automated_logging/admin/model_mirror.py
automated_logging/admin/request_event.py
automated_logging/admin/unspecified_event.py
automated_logging/apps.py
automated_logging/decorators.py
automated_logging/handlers.py
automated_logging/helpers/__init__.py
automated_logging/helpers/enums.py
automated_logging/helpers/exceptions.py
automated_logging/helpers/schemas.py
automated_logging/middleware.py
automated_logging/migrations/0001_initial.py
automated_logging/migrations/0002_auto_20180215_1540.py
automated_logging/migrations/0003_auto_20180216_0900.py
automated_logging/migrations/0004_auto_20180216_0935.py
automated_logging/migrations/0005_auto_20180216_0941.py
automated_logging/migrations/0006_auto_20180216_1004.py
automated_logging/migrations/0007_auto_20180216_1005.py
automated_logging/migrations/0008_auto_20180216_1005.py
automated_logging/migrations/0009_auto_20180216_1006.py
automated_logging/migrations/0010_auto_20180216_1430.py
automated_logging/migrations/0011_auto_20180216_1545.py
automated_logging/migrations/0012_auto_20180218_1101.py
automated_logging/migrations/0013_auto_20180218_1106.py
automated_logging/migrations/0014_auto_20180219_0859.py
automated_logging/migrations/0015_auto_20181229_2323.py
automated_logging/migrations/0016_auto_20200803_1917.py
automated_logging/migrations/0017_auto_20200819_1004.py
automated_logging/migrations/0018_decoratoroverrideexclusiontest_foreignkeytest_fullclassbasedexclusiontest_fulldecoratorbasedexclusio.py
automated_logging/migrations/__init__.py
automated_logging/models.py
automated_logging/settings.py
automated_logging/signals/__init__.py
automated_logging/signals/m2m.py
automated_logging/signals/request.py
automated_logging/signals/save.py
automated_logging/templates/dal/admin/view.html
automated_logging/tests/__init__.py
django_automated_logging-6.2.2.dist-info/LICENSE
django_automated_logging-6.2.2.dist-info/METADATA
django_automated_logging-6.2.2.dist-info/WHEEL
django_automated_logging-6.2.2.dist-info/RECORD
