Metadata-Version: 2.1
Name: django-automated-logging
Version: 6.2.2
Summary: Django Database Based Automated Logging - finally solved and done in a proper way.
Home-page: https://github.com/indietyp/django-automated-logging
License: MIT
Keywords: django,automation,tools,backend,logging
Author: Bilal Mahmoud
Author-email: bilalmahmoud@posteo.net
Requires-Python: >=3.10,<4
Classifier: Development Status :: 5 - Production/Stable
Classifier: Environment :: Web Environment
Classifier: Framework :: Django
Classifier: Framework :: Django :: 2.2
Classifier: Framework :: Django :: 3.0
Classifier: Framework :: Django :: 3.1
Classifier: Framework :: Django :: 3.2
Classifier: Intended Audience :: Developers
Classifier: License :: OSI Approved :: MIT License
Classifier: Programming Language :: Python :: 3
Classifier: Programming Language :: Python :: 3.10
Classifier: Programming Language :: Python :: 3.11
Classifier: Programming Language :: Python :: 3.12
Classifier: Programming Language :: Python :: 3.6
Classifier: Programming Language :: Python :: 3.7
Classifier: Programming Language :: Python :: 3.8
Classifier: Programming Language :: Python :: 3.9
Classifier: Topic :: Software Development :: Libraries :: Python Modules
Requires-Dist: django (>=3.2,<6)
Requires-Dist: django-ipware (>=6.0.4,<7.0.0)
Requires-Dist: django-picklefield (>=3.1,<4.0)
Requires-Dist: marshmallow (>=3.21.1,<4.0.0)
Project-URL: Repository, https://github.com/indietyp/django-automated-logging
